README.md
pyproject.toml
pulumi_aws/__init__.py
pulumi_aws/_enums.py
pulumi_aws/_inputs.py
pulumi_aws/_utilities.py
pulumi_aws/get_arn.py
pulumi_aws/get_availability_zone.py
pulumi_aws/get_availability_zones.py
pulumi_aws/get_billing_service_account.py
pulumi_aws/get_caller_identity.py
pulumi_aws/get_default_tags.py
pulumi_aws/get_ip_ranges.py
pulumi_aws/get_partition.py
pulumi_aws/get_region.py
pulumi_aws/get_regions.py
pulumi_aws/get_service.py
pulumi_aws/get_service_principal.py
pulumi_aws/outputs.py
pulumi_aws/provider.py
pulumi_aws/pulumi-plugin.json
pulumi_aws/py.typed
pulumi_aws.egg-info/PKG-INFO
pulumi_aws.egg-info/SOURCES.txt
pulumi_aws.egg-info/dependency_links.txt
pulumi_aws.egg-info/requires.txt
pulumi_aws.egg-info/top_level.txt
pulumi_aws/accessanalyzer/__init__.py
pulumi_aws/accessanalyzer/_inputs.py
pulumi_aws/accessanalyzer/analyzer.py
pulumi_aws/accessanalyzer/archive_rule.py
pulumi_aws/accessanalyzer/outputs.py
pulumi_aws/account/__init__.py
pulumi_aws/account/alternative_contact.py
pulumi_aws/account/get_primary_contact.py
pulumi_aws/account/primary_contact.py
pulumi_aws/account/region.py
pulumi_aws/acm/__init__.py
pulumi_aws/acm/_inputs.py
pulumi_aws/acm/certificate.py
pulumi_aws/acm/certificate_validation.py
pulumi_aws/acm/get_certificate.py
pulumi_aws/acm/outputs.py
pulumi_aws/acmpca/__init__.py
pulumi_aws/acmpca/_inputs.py
pulumi_aws/acmpca/certificate.py
pulumi_aws/acmpca/certificate_authority.py
pulumi_aws/acmpca/certificate_authority_certificate.py
pulumi_aws/acmpca/get_certificate.py
pulumi_aws/acmpca/get_certificate_authority.py
pulumi_aws/acmpca/outputs.py
pulumi_aws/acmpca/permission.py
pulumi_aws/acmpca/policy.py
pulumi_aws/alb/__init__.py
pulumi_aws/alb/_enums.py
pulumi_aws/alb/_inputs.py
pulumi_aws/alb/get_listener.py
pulumi_aws/alb/get_load_balancer.py
pulumi_aws/alb/get_target_group.py
pulumi_aws/alb/listener.py
pulumi_aws/alb/listener_certificate.py
pulumi_aws/alb/listener_rule.py
pulumi_aws/alb/load_balancer.py
pulumi_aws/alb/outputs.py
pulumi_aws/alb/target_group.py
pulumi_aws/alb/target_group_attachment.py
pulumi_aws/amp/__init__.py
pulumi_aws/amp/_inputs.py
